usbadc10/__init__.py
usbadc10/usbadc10.py
usbadc10/usbadc10-debian/libusbadc10.so
usbadc10/usbadc10-win32/usbadc10.dll
usbadc10/usbadc10-win64/usbadc10.dll
usbadc10-1.0.1.dist-info/METADATA
usbadc10-1.0.1.dist-info/WHEEL
usbadc10-1.0.1.dist-info/entry_points.txt
usbadc10-1.0.1.dist-info/license_files/LICENSE
usbadc10-1.0.1.dist-info/RECORD
