Metadata-Version: 2.1
Name: usbadc10
Version: 1.0.1
Summary: A python binding for USBADC10
Author-email: EPC MSU <info@physlab.ru>
License: Copyright (c) 2022 EPC MSU 
Classifier: License :: OSI Approved :: MIT License
Classifier: Operating System :: Microsoft :: Windows :: Windows 10
Classifier: Operating System :: Microsoft :: Windows :: Windows 11
Classifier: Operating System :: Microsoft :: Windows :: Windows 7
Classifier: Operating System :: Microsoft :: Windows :: Windows 8
Classifier: Operating System :: Microsoft :: Windows :: Windows 8.1
Classifier: Operating System :: POSIX :: Linux
Classifier: Programming Language :: C
Classifier: Programming Language :: Python :: 3
Classifier: Topic :: Scientific/Engineering
Classifier: Topic :: Software Development :: Embedded Systems
Classifier: Topic :: System :: Hardware :: Universal Serial Bus (USB) :: Communications Device Class (CDC)
Classifier: Topic :: System :: Networking
Requires-Python: >=3.6
